autohpsearch/__init__.py
autohpsearch/datasets/__init__.py
autohpsearch/datasets/dataloaders.py
autohpsearch/models/__init__.py
autohpsearch/models/llms.py
autohpsearch/models/llms_dual_head.py
autohpsearch/models/nn.py
autohpsearch/pipeline/__init__.py
autohpsearch/pipeline/cleaning.py
autohpsearch/pipeline/pipeline.py
autohpsearch/pipeline/reporter.py
autohpsearch/search/__init__.py
autohpsearch/search/grids.py
autohpsearch/search/hptuing.py
autohpsearch/search/reporting.py
autohpsearch/utils/__init__.py
autohpsearch/utils/context.py
autohpsearch/vis/__init__.py
autohpsearch/vis/evaluation_plots.py
autohpsearch/vis/reporting.py
autohpsearch-1.1.3.dist-info/licenses/LICENSE
autohpsearch-1.1.3.dist-info/METADATA
autohpsearch-1.1.3.dist-info/WHEEL
autohpsearch-1.1.3.dist-info/top_level.txt
autohpsearch-1.1.3.dist-info/RECORD
