Metadata-Version: 2.4
Name: autohpsearch
Version: 1.1.3
Summary: A package for automated hyper parameter tuning and machine learning workflows. Build an end-to-end pipeline or fine tune an LLM on consumer hardware in a few lines of code.
Author: Rudy van den Brink
License-Expression: GPL-3.0-only
Keywords: hyperparameter,tuning,optimization,machine learning
Classifier: Programming Language :: Python :: 3
Classifier: Topic :: Software Development :: Libraries
Requires-Python: >=3.9
License-File: LICENSE
Requires-Dist: asttokens==3.0.0
Requires-Dist: bs4==0.0.2
Requires-Dist: colorama==0.4.6
Requires-Dist: contractions==0.1.73
Requires-Dist: comm==0.2.2
Requires-Dist: datasets==4.0.0
Requires-Dist: debugpy==1.8.14
Requires-Dist: decorator==5.2.1
Requires-Dist: executing==2.2.0
Requires-Dist: imbalanced-learn==0.13.0
Requires-Dist: ipykernel==6.29.5
Requires-Dist: ipython==9.2.0
Requires-Dist: ipython_pygments_lexers==1.1.1
Requires-Dist: jedi==0.19.2
Requires-Dist: joblib==1.5.0
Requires-Dist: jupyter_client==8.6.3
Requires-Dist: jupyter_core==5.7.2
Requires-Dist: matplotlib-inline==0.1.7
Requires-Dist: matplotlib==3.10.3
Requires-Dist: nest-asyncio==1.6.0
Requires-Dist: numpy==2.2.5
Requires-Dist: packaging==25.0
Requires-Dist: pandas==2.2.3
Requires-Dist: parso==0.8.4
Requires-Dist: peft==0.16.0
Requires-Dist: platformdirs==4.3.8
Requires-Dist: prompt_toolkit==3.0.51
Requires-Dist: psutil==7.0.0
Requires-Dist: pure_eval==0.2.3
Requires-Dist: Pygments==2.19.1
Requires-Dist: python-dateutil==2.9.0.post0
Requires-Dist: pytz==2025.2
Requires-Dist: pywin32==310
Requires-Dist: pyzmq==26.4.0
Requires-Dist: scikit-learn==1.6.1
Requires-Dist: scikit-optimize==0.10.2
Requires-Dist: scipy==1.15.3
Requires-Dist: seaborn==0.13.2
Requires-Dist: six==1.17.0
Requires-Dist: stack-data==0.6.3
Requires-Dist: stanza==1.10.1
Requires-Dist: tabulate==0.9.0
Requires-Dist: textblob==0.19.0
Requires-Dist: threadpoolctl==3.6.0
Requires-Dist: tornado==6.4.2
Requires-Dist: tqdm==4.67.1
Requires-Dist: traitlets==5.14.3
Requires-Dist: typing_extensions==4.13.2
Requires-Dist: tzdata==2025.2
Requires-Dist: wcwidth==0.2.13
Requires-Dist: xgboost==3.0.1
Requires-Dist: torch==2.6.0
Requires-Dist: torchaudio==2.6.0
Requires-Dist: torchvision==0.21.0
Provides-Extra: dev
Requires-Dist: twine==6.1.0; extra == "dev"
Requires-Dist: setuptools==65.5.0; extra == "dev"
Requires-Dist: wheel==0.45.1; extra == "dev"
Requires-Dist: build==1.3.0; extra == "dev"
Dynamic: license-file
